Metadata-Version: 2.1
Name: urmapi
Version: 1.0.4
Summary: A Decentralized Package Manager.
Home-page: https://nokodaaddictions.github.io
Author: NoKodaAddictions
Author-email: nokodaaddictions@gmail.com
License: MIT
Platform: UNKNOWN
License-File: LICENSE
